decorated_paho_mqtt/__init__.py
decorated_paho_mqtt/mqtt_framework.py
decorated_paho_mqtt-1.1.1.dist-info/licenses/LICENSE
decorated_paho_mqtt-1.1.1.dist-info/METADATA
decorated_paho_mqtt-1.1.1.dist-info/WHEEL
decorated_paho_mqtt-1.1.1.dist-info/top_level.txt
decorated_paho_mqtt-1.1.1.dist-info/RECORD
