Metadata-Version: 2.4
Name: decorated_paho_mqtt
Version: 1.1.1
Summary: Wrapper for Paho MQTT with declarative subscriptions and topic parsing utilities
Home-page: https://github.com/phi1010/decorated-paho-mqtt
Author: Phillip Kuhrt
Author-email: mail@phi1010.com
Classifier: Programming Language :: Python :: 3
Classifier: License :: OSI Approved :: BSD License
Classifier: Operating System :: OS Independent
Requires-Python: >=3.7
License-File: LICENSE
Requires-Dist: paho-mqtt
Dynamic: author
Dynamic: author-email
Dynamic: classifier
Dynamic: description
Dynamic: description-content-type
Dynamic: home-page
Dynamic: license-file
Dynamic: requires-dist
Dynamic: requires-python
Dynamic: summary
